triggers/__init__.py
triggers/admin.py
triggers/apps.py
triggers/migrations/0001_initial.py
triggers/migrations/0002_auto_20221021_2046.py
triggers/migrations/0003_event_delay.py
triggers/migrations/__init__.py
triggers/models.py
triggers/tasks.py
dj_triggers-1.0.1.dist-info/LICENSE
dj_triggers-1.0.1.dist-info/METADATA
dj_triggers-1.0.1.dist-info/WHEEL
dj_triggers-1.0.1.dist-info/RECORD
