Metadata-Version: 2.1
Name: dj-triggers
Version: 1.0.1
Summary: A Triggers system for Django made for implementing event-based business logic configurable through the Django admin site.
Home-page: https://github.com/cockpithq/django-triggers
License: BSD-3-Clause
Keywords: django,triggers
Author: Dmitry Kolyagin
Author-email: dmitry.kolyagin@gmail.com
Requires-Python: >=3.7,<4.0
Classifier: Framework :: Django :: 3
Classifier: Framework :: Django :: 4
Classifier: License :: OSI Approved :: BSD License
Classifier: Programming Language :: Python :: 3
Classifier: Programming Language :: Python :: 3.7
Classifier: Programming Language :: Python :: 3.8
Classifier: Programming Language :: Python :: 3.9
Classifier: Programming Language :: Python :: 3.10
Classifier: Programming Language :: Python :: 3.11
Requires-Dist: Django (>=3)
Requires-Dist: celery (>=4.4)
Requires-Dist: django-polymorphic (>=3,<4)
Project-URL: Repository, https://github.com/cockpithq/django-triggers
